ptap/__init__.py
ptap/assembly.py
ptap/config.py
ptap/file_reader.py
ptap/github.py
ptap/main.py
ptap/visualizer.py
ptap-1.2.1.dist-info/licenses/LICENSE
ptap-1.2.1.dist-info/METADATA
ptap-1.2.1.dist-info/WHEEL
ptap-1.2.1.dist-info/entry_points.txt
ptap-1.2.1.dist-info/top_level.txt
ptap-1.2.1.dist-info/RECORD
