Metadata-Version: 2.4
Name: ptap
Version: 1.2.1
Summary: The best tool to generate AI prompts from code projects and make any AI understand a whole project!
Home-page: https://github.com/Far3000-YT/PTAP
Author: Far3k
Author-email: far3000yt@gmail.com
License: MIT
Classifier: Programming Language :: Python :: 3
Classifier: License :: OSI Approved :: MIT License
Classifier: Operating System :: OS Independent
Requires-Python: >=3.7
License-File: LICENSE
Requires-Dist: requests
Requires-Dist: pyperclip
Dynamic: author
Dynamic: author-email
Dynamic: classifier
Dynamic: description
Dynamic: description-content-type
Dynamic: home-page
Dynamic: license
Dynamic: license-file
Dynamic: requires-dist
Dynamic: requires-python
Dynamic: summary
